gjdatac_api/__init__.py
gjdatac_api/data_api_class.py
gjdatac_api/dict_data.py
gjdatac_api/dolphin_db_info.py
gjdatac_project-0.0.1.dist-info/METADATA
gjdatac_project-0.0.1.dist-info/WHEEL
gjdatac_project-0.0.1.dist-info/top_level.txt
gjdatac_project-0.0.1.dist-info/RECORD
