Metadata-Version: 2.1
Name: gjdatac-project
Version: 0.0.1
Summary: 主动管理项目第一版(部分接口)
Home-page: UNKNOWN
Author: yin
Author-email: 2018209921@qq.com
License: UNKNOWN
Platform: UNKNOWN
Requires-Python: >3.6
Requires-Dist: dolphindb ==3.0.1.0
Requires-Dist: holidays ==0.53
Requires-Dist: numpy ==1.26.3
Requires-Dist: pandas ==2.2.0
